odoo/addons/sale_channel_search_engine/README.rst
odoo/addons/sale_channel_search_engine/__init__.py
odoo/addons/sale_channel_search_engine/__manifest__.py
odoo/addons/sale_channel_search_engine/i18n/it.po
odoo/addons/sale_channel_search_engine/i18n/sale_channel_search_engine.pot
odoo/addons/sale_channel_search_engine/models/__init__.py
odoo/addons/sale_channel_search_engine/models/sale_channel.py
odoo/addons/sale_channel_search_engine/models/se_backend.py
odoo/addons/sale_channel_search_engine/models/se_binding.py
odoo/addons/sale_channel_search_engine/models/se_index.py
odoo/addons/sale_channel_search_engine/models/se_indexable_record.py
odoo/addons/sale_channel_search_engine/readme/CONTRIBUTORS.rst
odoo/addons/sale_channel_search_engine/readme/DESCRIPTION.rst
odoo/addons/sale_channel_search_engine/readme/HISTORY.rst
odoo/addons/sale_channel_search_engine/readme/newsfragments/.gitignore
odoo/addons/sale_channel_search_engine/static/description/icon.png
odoo/addons/sale_channel_search_engine/static/description/index.html
odoo/addons/sale_channel_search_engine/views/sale_channel_view.xml
odoo_addon_sale_channel_search_engine-16.0.0.1.2.2.dist-info/METADATA
odoo_addon_sale_channel_search_engine-16.0.0.1.2.2.dist-info/WHEEL
odoo_addon_sale_channel_search_engine-16.0.0.1.2.2.dist-info/top_level.txt
odoo_addon_sale_channel_search_engine-16.0.0.1.2.2.dist-info/RECORD
