Metadata-Version: 2.1
Name: odoo-addon-sale_channel_search_engine
Version: 16.0.0.1.2.2
Summary: Abstract module for configuring a search engine on a sale channel
Home-page: https://github.com/OCA/sale-channel
Author: Akretion, Odoo Community Association (OCA)
Author-email: support@odoo-community.org
License: AGPL-3
Classifier: Programming Language :: Python
Classifier: Framework :: Odoo
Classifier: Framework :: Odoo :: 16.0
Classifier: License :: OSI Approved :: GNU Affero General Public License v3
Classifier: Development Status :: 3 - Alpha
Requires-Python: >=3.10
Requires-Dist: odoo-addon-connector-search-engine<16.1dev,>=16.0dev
Requires-Dist: odoo-addon-sale-channel<16.1dev,>=16.0dev
Requires-Dist: odoo<16.1dev,>=16.0a
